paraty_commit_python2/.pre-commit-config.yaml
paraty_commit_python2/__init__.py
paraty_commit_python2/mypy.ini
paraty_commit_python2/precommit.py
paraty_commit_python2/pylintrc
paraty_commit_python2-0.2.5.dist-info/LICENSE
paraty_commit_python2-0.2.5.dist-info/METADATA
paraty_commit_python2-0.2.5.dist-info/WHEEL
paraty_commit_python2-0.2.5.dist-info/entry_points.txt
paraty_commit_python2-0.2.5.dist-info/top_level.txt
paraty_commit_python2-0.2.5.dist-info/RECORD
