Metadata-Version: 2.1
Name: paraty-commit-python2
Version: 0.2.5
Summary: Una biblioteca personalizada
Home-page: UNKNOWN
Author: José Luis Villada
Author-email: jlvillada@paratytech.com
License: UNKNOWN
Platform: UNKNOWN
Classifier: Development Status :: 5 - Production/Stable
Classifier: Intended Audience :: Developers
Classifier: License :: OSI Approved :: MIT License
Classifier: Programming Language :: Python :: 2
Classifier: Programming Language :: Python :: 2.7
Classifier: Programming Language :: Python :: 2 :: Only
Requires-Python: >=2.7, <3
Requires-Dist: colorama
Requires-Dist: pylint (==1.9.5)
